shared_utils/__init__.py
shared_utils/serialization_utils.py
shared_utils/clients/__init__.py
shared_utils/clients/age_client.py
shared_utils/clients/async_age_client.py
shared_utils/clients/async_db_client.py
shared_utils/clients/async_s3_client.py
shared_utils/clients/db_client.py
shared_utils/clients/mock_client.py
shared_utils/clients/redis_client.py
shared_utils/clients/utils/__init__.py
shared_utils/clients/utils/age_client_base.py
shared_utils/clients/utils/db_client_base.py
shared_utils/clients/utils/postgres_client.py
shared_utils/event_models/AllChunksProcessedEvent.py
shared_utils/event_models/DocumentIngestRequestEvent.py
shared_utils/event_models/KnowledgeGraphUpdatedEvent.py
shared_utils/event_models/KnowledgeGraphVisualsGeneratedEvent.py
shared_utils/event_models/ProcessChunkRequestEvent.py
shared_utils/event_models/__init__.py
shared_utils/queries/__init__.py
shared_utils/queries/apache_age.py
shared_utils/queries/async_apache_age.py
shared_utils/queries/async_chunk_graphs.py
shared_utils/queries/async_chunks.py
shared_utils/queries/async_documents.py
shared_utils/queries/async_ingestion_jobs.py
shared_utils/queries/async_layouts.py
shared_utils/queries/chunk_graphs.py
shared_utils/queries/chunks.py
shared_utils/queries/cytoscape_elements.py
shared_utils/queries/documents.py
shared_utils/queries/ingestion_jobs.py
shared_utils/response_models/DocumentUploadResponse.py
shared_utils/response_models/GetDocumentByIDResponse.py
shared_utils/response_models/GetDocumentsResponse.py
shared_utils/response_models/IngestionJobStatusResponse.py
shared_utils/response_models/IngestionRequestResponse.py
shared_utils/response_models/UserPromptResponse.py
shared_utils/response_models/__init__.py
shared_utils/sql_models/Chunk.py
shared_utils/sql_models/ChunkGraph.py
shared_utils/sql_models/CytoscapeElements.py
shared_utils/sql_models/DocumentMetadata.py
shared_utils/sql_models/IngestionJob.py
shared_utils/sql_models/__init__.py
insurgentai_shared_utils-0.4.22.dist-info/METADATA
insurgentai_shared_utils-0.4.22.dist-info/WHEEL
insurgentai_shared_utils-0.4.22.dist-info/top_level.txt
insurgentai_shared_utils-0.4.22.dist-info/RECORD
