Metadata-Version: 2.4
Name: insurgentai_shared_utils
Version: 0.4.22
Summary: A collection of shared utility functions for InsurgentAI microservices.
Requires-Python: >=3.12
Requires-Dist: fastapi[standard]>=0.115.12
Requires-Dist: psycopg[binary,pool]>=3.2.6
Requires-Dist: pydantic>=2.11.7
Requires-Dist: sqlmodel>=0.0.24
Requires-Dist: redis
Requires-Dist: aioboto3
Requires-Dist: asyncpg>=0.29.0
Requires-Dist: sqlalchemy[asyncio]>=2.0.0
